utf8config/__init__.py
utf8config/__init__.pyc
utf8config/core.py
utf8config/core.pyc
utf8config/io.py
utf8config/io.pyc
utf8config/__pycache__/__init__.cpython-34.pyc
utf8config/__pycache__/__init__.cpython-35.pyc
utf8config/__pycache__/__init__.cpython-36.pyc
utf8config/__pycache__/core.cpython-34.pyc
utf8config/__pycache__/core.cpython-35.pyc
utf8config/__pycache__/core.cpython-36.pyc
utf8config/__pycache__/io.cpython-34.pyc
utf8config/__pycache__/io.cpython-35.pyc
utf8config/__pycache__/io.cpython-36.pyc
utf8config-0.0.2.dist-info/DESCRIPTION.rst
utf8config-0.0.2.dist-info/METADATA
utf8config-0.0.2.dist-info/RECORD
utf8config-0.0.2.dist-info/WHEEL
utf8config-0.0.2.dist-info/metadata.json
utf8config-0.0.2.dist-info/top_level.txt
